README.md
setup.py
gdockutils/__init__.py
gdockutils/certificates.py
gdockutils/cli.py
gdockutils/db.py
gdockutils/gprun.py
gdockutils/prepare.py
gdockutils/secret.py
gdockutils/ui.py
gdockutils.egg-info/PKG-INFO
gdockutils.egg-info/SOURCES.txt
gdockutils.egg-info/dependency_links.txt
gdockutils.egg-info/entry_points.txt
gdockutils.egg-info/requires.txt
gdockutils.egg-info/top_level.txt