Metadata-Version: 2.1
Name: gdockutils
Version: 0.5.3
Summary: Galaktika Solutions - Docker Utilities
Home-page: https://github.com/galaktika-solutions/gDockUtils
Author: Richard Bann
Author-email: richardbann@gmail.com
License: MIT
Platform: UNKNOWN
Classifier: License :: OSI Approved :: MIT License
Classifier: Programming Language :: Python :: 3.6
